machkit/__init__.py
machkit/machkit.py
machkit/common/__init__.py
machkit/common/config.py
machkit/common/datapp_response.py
machkit/common/quota_manager.py
machkit/common/user_manager.py
machkit/controller/__init__.py
machkit/controller/batches_controller.py
machkit/controller/file_controller.py
machkit/controller/label_controller.py
machkit/controller/requirement_controller.py
machkit/controller/user_controller.py
machkit/services/__init__.py
machkit/services/base_request.py
machkit/services/batches_service.py
machkit/services/file_service.py
machkit/services/label_service.py
machkit/services/requirement_service.py
machkit/services/user_service.py
machkit/utils/__init__.py
machkit/utils/file_utils.py
tests/__init__.py
tests/test_basic.py
tests/test_batch.py
tests/test_file.py
tests/test_label.py
tests/test_login.py
tests/test_otp.py
tests/test_requirement.py
tests/test_token.py
tests/test_user.py
machkit_d-0.1.1.dist-info/METADATA
machkit_d-0.1.1.dist-info/WHEEL
machkit_d-0.1.1.dist-info/top_level.txt
machkit_d-0.1.1.dist-info/RECORD
